e_lims_core/__init__.py
e_lims_core/e_lims_core.py
e_lims_core/py.typed
e_lims_core-0.0.2.dist-info/LICENSE
e_lims_core-0.0.2.dist-info/METADATA
e_lims_core-0.0.2.dist-info/WHEEL
e_lims_core-0.0.2.dist-info/RECORD
