Metadata-Version: 2.1
Name: e_lims_core
Version: 0.0.2
Summary: e-lims core
License: MIT
Author: Fabien Meyer
Author-email: fabien-meyer@outlook.com
Requires-Python: >=3.12,<4.0
Classifier: License :: OSI Approved :: MIT License
Classifier: Programming Language :: Python :: 3
Classifier: Programming Language :: Python :: 3.12
Requires-Dist: typing-extensions (>=4.12.2,<5.0.0)
